cosci/__init__.py
cosci/__version__.py
cosci/api_client.py
cosci/auth.py
cosci/client.py
cosci/config.py
cosci/exceptions.py
cosci/logger.py
cosci/models.py
cosci/session.py
cosci/utils.py
py_cosci-0.1.2.dist-info/licenses/LICENSE
py_cosci-0.1.2.dist-info/METADATA
py_cosci-0.1.2.dist-info/WHEEL
py_cosci-0.1.2.dist-info/top_level.txt
py_cosci-0.1.2.dist-info/RECORD
