Metadata-Version: 2.4
Name: py-cosci
Version: 0.1.2
Summary: Python SDK for Google's Co-Scientist Discovery Engine
Home-page: https://github.com/arunpshankar/cosci.git
Author: Co-Scientist Team
Author-email: Co-Scientist Team <arunpshankar@google.com>
License: MIT
Project-URL: Repository, https://github.com/arunpshankar/cosci
Keywords: coscientist,google,ai,research,ideation,discovery-engine
Requires-Python: >=3.8
License-File: LICENSE
Requires-Dist: requests>=2.28.0
Requires-Dist: google-auth>=2.16.0
Requires-Dist: google-auth-oauthlib>=0.4.6
Requires-Dist: google-auth-httplib2>=0.1.0
Provides-Extra: dev
Requires-Dist: pytest>=7.0; extra == "dev"
Requires-Dist: black>=22.0; extra == "dev"
Requires-Dist: flake8>=4.0; extra == "dev"
Requires-Dist: mypy>=0.990; extra == "dev"
Dynamic: author
Dynamic: home-page
Dynamic: license-file
Dynamic: requires-python
